setup.cfg
setup.py
dynamo/__init__.py
dynamo/main.py
dynamo/remover.py
dynamo_mypy.egg-info/PKG-INFO
dynamo_mypy.egg-info/SOURCES.txt
dynamo_mypy.egg-info/dependency_links.txt
dynamo_mypy.egg-info/entry_points.txt
dynamo_mypy.egg-info/top_level.txt