Metadata-Version: 1.1
Name: dynamo-mypy
Version: 0.0.16
Summary: remove annotations
Home-page: https://github.com/alehander42/dynamo
Author: Alexander Ivanov
Author-email: alehander42@gmail.com
License: MIT
Download-URL: https://github.com/alehander42/dynamo/archive/v0.0.1.tar.gz
Keywords: mypy,annotation
Platform: UNKNOWN
Classifier: Development Status :: 4 - Beta
Classifier: Programming Language :: Python
Classifier: Programming Language :: Python :: 3.2
Classifier: Programming Language :: Python :: 3.3
Classifier: Programming Language :: Python :: 3.4
Classifier: Intended Audience :: Developers
Classifier: License :: OSI Approved :: MIT License
